{
  "vehicles": {
    "COMMENT_": "[Vehicles info] - END",
    "_COMMENT": "[Vehicles info] - START",
    "__COMMENT": "Vehicle Subclass: car, van, truck.",
    "___COMMENT": "Vehicle Type: VehicleWithBicycleKinematics, VehicleDoubleIntegratorKinematics, VehicleSingleIntegratorKinematics",
    "info": [
      {
        "id": 0,
        "init_state": {
          "acceleration": 0.0,
          "angle": -2.8609507031905816,
          "curvature": 0.0,
          "steer": 0.0,
          "velocity": 3.5014191209604424,
          "x": -4865.266839149291,
          "y": -6838.66536263614
        },
        "params": {
          "front_suspension": 0.93,
          "length": 4.5,
          "max_lateral_acc": 2.0,
          "max_longitudinal_acc": 2.0,
          "max_steering_angle": 45.0,
          "rear_suspension": 1.1,
          "wheel_base": 2.85,
          "width": 1.9
        },
        "subclass": "car",
        "type": "VehicleWithBicycleKinematics"
      }
    ],
    "num": 1
  }
}